blxr_rlp/__init__.py
blxr_rlp/codec.py
blxr_rlp/exceptions.py
blxr_rlp/lazy.py
blxr_rlp/utils.py
blxr_rlp/utils_py2.py
blxr_rlp/utils_py3.py
blxr_rlp/sedes/__init__.py
blxr_rlp/sedes/big_endian_int.py
blxr_rlp/sedes/binary.py
blxr_rlp/sedes/lists.py
blxr_rlp/sedes/raw.py
blxr_rlp-0.6.0.dist-info/LICENSE
blxr_rlp-0.6.0.dist-info/METADATA
blxr_rlp-0.6.0.dist-info/WHEEL
blxr_rlp-0.6.0.dist-info/top_level.txt
blxr_rlp-0.6.0.dist-info/RECORD
