Metadata-Version: 2.1
Name: blxr-rlp
Version: 0.6.0
Summary: A package for encoding and decoding data in and from Recursive Length Prefix notation
Home-page: https://github.com/bloXroute-Labs/pyrlp
Author: jnnk
Author-email: jnnknnj@gmail.com
License: MIT
Keywords: rlp ethereum
Platform: UNKNOWN
Classifier: Development Status :: 2 - Pre-Alpha
Classifier: Intended Audience :: Developers
Classifier: License :: OSI Approved :: BSD License
Classifier: Natural Language :: English
Classifier: Programming Language :: Python :: 2
Classifier: Programming Language :: Python :: 2.7
Classifier: Programming Language :: Python :: 3
Classifier: Programming Language :: Python :: 3.3
Classifier: Programming Language :: Python :: 3.4
